[{"id": 0, "competitors": [{"id": 1, "pokemon": [131, 248, 468, 534, 59, 356]}, {"id": 2, "pokemon": [130, "53-a", 700, 143, 609, 464]}], "winner": 2}, {"id": 1, "competitors": [{"id": 3, "pokemon": [858, 530, 468, 350, 781, 248]}, {"id": 4, "pokemon": [887, 448, 468, 131, 59, 861]}], "winner": 3}, {"id": 2, "competitors": [{"id": 3, "pokemon": [858, 530, 468, 350, 781, 248]}, {"id": 1, "pokemon": [576, 510, 700, 248, 324, 598]}], "winner": 1}, {"id": 3, "competitors": [{"id": 4, "pokemon": ["", "", "", "", "", ""]}, {"id": 2, "pokemon": ["", "", "", "", "", ""]}], "winner": 2}, {"id": 4, "competitors": [{"id": 3, "pokemon": [887, 356, 730, 727, 781, 468]}, {"id": 2, "pokemon": [35, 660, 468, 598, 609, 350]}], "winner": 2}, {"id": 5, "competitors": [{"id": 4, "pokemon": [448, 887, 131, 468, 59, 861]}, {"id": 1, "pokemon": [208, 350, 812, 426, 356, "876-f"]}], "winner": 1}, {"id": 6, "competitors": [{"id": 4, "pokemon": [186, 230, 468, 214, 553, "105-a"]}, {"id": 1, "pokemon": [237, 248, 887, "479-h", 468, 184]}], "winner": 1}, {"id": 7, "competitors": [{"id": 3, "pokemon": [9, 727, 186, 468, 812, 26]}, {"id": 2, "pokemon": [591, 639, 186, 230, 468, 637]}], "winner": 2}, {"id": 8, "competitors": [{"id": 2, "pokemon": [3, 6, 324, 468, 248, 356]}, {"id": 5, "pokemon": [3, 6, 324, 468, 248, 356]}], "winner": 2}, {"id": 9, "competitors": [{"id": 4, "pokemon": [812, 468, 131, "105-a", 248, 233]}, {"id": 6, "pokemon": [233, 639, 727, "876-f", 184, 65]}], "winner": 6}, {"id": 10, "competitors": [{"id": 3, "pokemon": [887, 248, 468, 184, 237, 815]}, {"id": 7, "pokemon": [130, 73, 279, 9, 211, 91]}], "winner": 7}, {"id": 11, "competitors": [{"id": 3, "pokemon": [143, 727, 530, 468, 887, "479-w"]}, {"id": 6, "pokemon": [727, "876-m", "80-g", 468, 598, 423]}], "winner": 3}, {"id": 12, "competitors": [{"id": 2, "pokemon": [812, 184, "876-f", "105-a", 858, 233]}, {"id": 8, "pokemon": [812, 184, "876-f", "105-a", 858, 233]}], "winner": 2}, {"id": 13, "competitors": [{"id": 4, "pokemon": [233, "876-m", 184, 212, 781, 858]}, {"id": 9, "pokemon": [547, 131, 35, 186, 706, 847]}], "winner": 4}, {"id": 14, "competitors": [{"id": 5, "pokemon": [882, 350, 849, 663, "892-rss", 632]}, {"id": 7, "pokemon": [9, 279, 211, 130, 73, 91]}], "winner": 5}, {"id": 15, "competitors": [{"id": 2, "pokemon": ["26-a", 637, "876-f", 887, 871, "892-ss"]}, {"id": 6, "pokemon": [861, 858, 136, 465, 199, 463]}], "winner": 2}, {"id": 16, "competitors": [{"id": 3, "pokemon": [206, 812, 468, 591, 815, 350]}, {"id": 10, "pokemon": ["892-rss", 815, 468, 143, "222-g", 748]}], "winner": 3}, {"id": 17, "competitors": [{"id": 1, "pokemon": [601, 812, 350, 727, 858, "876-f"]}, {"id": 9, "pokemon": [730, 617, "105-a", "876-f", 233, 770]}], "winner": 1}, {"id": 18, "competitors": [{"id": 11, "pokemon": [302, 474, 663, 468, "876-m", 815]}, {"id": 7, "pokemon": [130, 73, 279, 9, 211, 91]}], "winner": 11}, {"id": 19, "competitors": [{"id": 3, "pokemon": [591, 815, 812, 350, 695, 468]}, {"id": 12, "pokemon": [826, 884, 547, 639, 130, 468]}], "winner": 3}, {"id": 20, "competitors": [{"id": 1, "pokemon": ["53-a", 591, 628, 727, 812, 678]}, {"id": 6, "pokemon": [534, 887, 131, "38-a", 873, 778]}], "winner": 1}, {"id": 21, "competitors": [{"id": 4, "pokemon": [468, 887, 727, 131, 812, 212]}, {"id": 11, "pokemon": [184, 727, 815, 628, 468, 591]}], "winner": 4}, {"id": 22, "competitors": [{"id": 2, "pokemon": [186, 230, "892-rss", 591, 468, 462]}, {"id": 1, "pokemon": [134, 727, 248, 468, 3, 324]}], "winner": 2}, {"id": 23, "competitors": [{"id": 12, "pokemon": [820, 248, 130, 468, 726, 765]}, {"id": 7, "pokemon": [12, 815, 839, 730, 884, 861]}], "winner": 12}, {"id": 24, "competitors": [{"id": 3, "pokemon": [869, 530, 130, 591, "892-ss", 663]}, {"id": 6, "pokemon": [508, 248, 468, 815, 727, "892-rss"]}], "winner": 3}, {"id": 25, "competitors": [{"id": 13, "pokemon": ["876-m", 639, 727, "892-rss", 591, 823]}, {"id": 6, "pokemon": [73, 553, 233, 812, "105-a", 468]}], "winner": 13}, {"id": 26, "competitors": [{"id": 3, "pokemon": [530, 248, 468, 887, 727, 591]}, {"id": 9, "pokemon": [534, 35, 855, "892-ss", "876-f", 143]}], "winner": 3}, {"id": 27, "competitors": [{"id": 2, "pokemon": [186, 230, "892-rss", 591, 468, 462]}, {"id": 7, "pokemon": [186, 591, 462, 750, 865, 715]}], "winner": 7}, {"id": 28, "competitors": [{"id": 13, "pokemon": [815, 59, 130, 547, 638, 841]}, {"id": 7, "pokemon": [186, 591, 462, 750, 865, 715]}], "winner": 7}, {"id": 29, "competitors": [{"id": 3, "pokemon": [632, 591, 130, 350, 609, 248]}, {"id": 14, "pokemon": [832, 887, 35, 823, 59, 131]}], "winner": 14}]